setup.py
bungee/__init__.py
bungee/const.py
bungee/exception.py
bungee/field.py
bungee/json_document.py
bungee/model.py
bungee/query.py
bungee/util.py
bungee.egg-info/PKG-INFO
bungee.egg-info/SOURCES.txt
bungee.egg-info/dependency_links.txt
bungee.egg-info/requires.txt
bungee.egg-info/top_level.txt
bungee/tests/__init__.py
bungee/tests/model_tests.py
bungee/tests/query_expression_tests.py