Metadata-Version: 1.1
Name: bungee
Version: 0.1
Summary: Python models and query expressions for ElasticSearch
Home-page: https://github.com/wan/bungee
Author: Andrew Wan
Author-email: andrew@thatsnumberwan.com
License: BSD
Platform: UNKNOWN
Classifier: Development Status :: 3 - Alpha
Classifier: Intended Audience :: Developers
Classifier: License :: OSI Approved :: BSD License
Classifier: Programming Language :: Python
Classifier: Operating System :: OS Independent
Classifier: Topic :: Internet :: WWW/HTTP :: Indexing/Search
